{
  "language": "c++",
  "question": "Implement a `MyString` class that dynamically allocates memory for a character array (C-style string). Provide a constructor that takes a `const char*` to initialize the string. Crucially, implement a copy constructor to perform a deep copy, preventing issues like double-freeing or shared pointers when `MyString` objects are copied.",
  "test_cases": [
    {
      "input": "MyString s1(\"Hello, World!\"); MyString s2 = s1; MyString s3;",
      "expected": "s1: Hello, World!\ns2: Hello, World!\ns3: \ns1 data address: <distinct_address_1>\ns2 data address: <distinct_address_2>"
    }
  ],
  "driver": "The `main` function demonstrates class construction and copy construction.",
  "code_quality": 1,
  "correctness": 0,
  "error_type": "Syntax Error",
  "errors": []
}