{
  "language": "c++",
  "question": "Implement a recursive C++ function `int fibonacci(int n)` that calculates the Nth Fibonacci number (where F(0)=0, F(1)=1, F(n)=F(n-1)+F(n-2)). In `main`, ask the user for an integer `N` and print the `N`th Fibonacci number.",
  "test_cases": [
    { "input": "10", "expected": "The 10th Fibonacci number is: 55\n" },
    { "input": "20", "expected": "The 20th Fibonacci number is: 6765\n" },
    { "input": "3", "expected": "The 3th Fibonacci number is: 2\n" },
    { "input": "35", "expected": "The 35th Fibonacci number is: 9227465\n" }
  ],
  "driver": "int main() {\n    int N;\n    std::cin >> N;\n    if (N < 0) {\n        std::cerr << \"Error: N must be a non-negative integer for this calculation.\" << std::endl;\n        return 1;\n    }\n    int result = fibonacci(N);\n    std::cout << \"The \" << N << \"th Fibonacci number is: \" << result << std::endl;\n    return 0;\n}",
  "code_quality": 3,
  "correctness": 9,
  "error_type": "Readability / Efficiency Issue",
  "errors": [
    "The recursive implementation of `fibonacci` is highly inefficient due to redundant calculations (O(2^N) time complexity). For larger values of N (e.g., N > 30-40), the computation time will be excessively long, potentially leading to timeouts or stack overflow. This is a classic example of an exponential time complexity issue without memoization, significantly impacting performance."
  ]
}