{
  "language": "c++",
  "question": "Implement a function called calculateVolume that calculates and returns the volume of a cube given the length of its side. Signature: double calculateVolume(double sideLength);",
  "test_cases": [
    {
      "input": "3",
      "expected": "27"
    },
    {
      "input": "2.5",
      "expected": "15.625"
    },
    {
      "input": "0",
      "expected": "0"
    }
  ],
  "driver": "#include <iostream>\nusing namespace std;\n\ndouble calculateVolume(double);\n\nint main() {\n    double s;\n    while (cin >> s) {\n        cout << calculateVolume(s) << endl;\n    }\n    return 0;\n}",
  "code_quality": 1,
  "correctness": 0,
  "error_type": "Syntax Error",
  "errors": [
    "Missing semicolon after return statement"
  ]
}